tests/__init__.py
tests/unittest/__init__.py
tests/unittest/jj_spec_validator/__init__.py
tests/unittest/jj_spec_validator/test_output.py
tests/unittest/jj_spec_validator/test_spec.py
tests/unittest/jj_spec_validator/test_validate_spec.py
tests/unittest/jj_spec_validator/test_validator.py
vedro_spec_validator/__init__.py
vedro_spec_validator/__version__.py
vedro_spec_validator/_spec_validator.py
vedro_spec_validator/_spec_validator_plugin.py
vedro_spec_validator/jj_spec_validator/__init__.py
vedro_spec_validator/jj_spec_validator/_config.py
vedro_spec_validator/jj_spec_validator/cli.py
vedro_spec_validator/jj_spec_validator/output.py
vedro_spec_validator/jj_spec_validator/spec.py
vedro_spec_validator/jj_spec_validator/validate_spec.py
vedro_spec_validator/jj_spec_validator/validator.py
vedro_spec_validator/jj_spec_validator/utils/__init__.py
vedro_spec_validator/jj_spec_validator/utils/_cacheir.py
vedro_spec_validator/jj_spec_validator/utils/_common.py
vedro_spec_validator/jj_spec_validator/utils/_refiner.py
vedro_spec_validator/jj_spec_validator/utils/_spec_matcher.py
vedro_spec_validator-0.1.15.dist-info/licenses/LICENSE
vedro_spec_validator-0.1.15.dist-info/METADATA
vedro_spec_validator-0.1.15.dist-info/WHEEL
vedro_spec_validator-0.1.15.dist-info/entry_points.txt
vedro_spec_validator-0.1.15.dist-info/top_level.txt
vedro_spec_validator-0.1.15.dist-info/RECORD
