Metadata-Version: 2.4
Name: vedro-spec-validator
Version: 0.1.15
Summary: Vedro Spec Validator plugin
Home-page: https://github.com/Maestoz/vedro-spec-validator
Author: Sam Roz
Author-email: rolez777@gmail.com
License: Apache-2.0
Classifier: License :: OSI Approved :: Apache Software License
Classifier: Programming Language :: Python :: 3.10
Classifier: Programming Language :: Python :: 3.11
Requires-Python: >=3.10
License-File: LICENSE
Requires-Dist: vedro<2.0,>=1.10
Requires-Dist: httpx<1.0.0,>=0.27.0
Requires-Dist: jj<3.0.0,>=2.11.0
Requires-Dist: schemax<3.0.0,>=2.0.0
Requires-Dist: d42<3.0.0,>=2.0.0
Requires-Dist: click<9.0.0,>=8.0.0
Dynamic: author
Dynamic: author-email
Dynamic: classifier
Dynamic: description
Dynamic: description-content-type
Dynamic: home-page
Dynamic: license
Dynamic: license-file
Dynamic: requires-dist
Dynamic: requires-python
Dynamic: summary
